Metadata-Version: 1.1
Name: pytest-apistellar
Version: 0.2.0
Summary: apistellar plugin for pytest. 
Home-page: https://www.github.com/ShichaoMa/apistellar
Author: cn
Author-email: cnaafhvk@foxmail.com
License: MIT
Keywords: pytest,apistellar
Platform: UNKNOWN
Classifier: Framework :: Pytest
Classifier: License :: OSI Approved :: MIT License
Classifier: Programming Language :: Python :: 3.6
Classifier: Intended Audience :: Developers
Classifier: Operating System :: Unix
